myspider/__init__.py
myspider/__main__.py
myspider/mp/__init__.py
myspider/mp/parse_mplist.py
myspider/sogou/__init__.py
myspider/sogou/weixin.py
myspider-1.1.0.dist-info/METADATA
myspider-1.1.0.dist-info/WHEEL
myspider-1.1.0.dist-info/entry_points.txt
myspider-1.1.0.dist-info/top_level.txt
myspider-1.1.0.dist-info/RECORD
